courtrss/__init__.py
courtrss/rss_feed.py
courtrss-0.1.4.dist-info/LICENSE
courtrss-0.1.4.dist-info/METADATA
courtrss-0.1.4.dist-info/WHEEL
courtrss-0.1.4.dist-info/entry_points.txt
courtrss-0.1.4.dist-info/top_level.txt
courtrss-0.1.4.dist-info/RECORD
