Metadata-Version: 2.1
Name: courtrss
Version: 0.1.4
Summary: A package to monitor court RSS feeds for keywords.
Home-page: https://github.com/jonmest/CourtRSS
Author: Jon Cavallie Mester
Classifier: Programming Language :: Python :: 3
Classifier: License :: OSI Approved :: MIT License
Classifier: Operating System :: OS Independent
Requires-Python: >=3.6
License-File: LICENSE
Requires-Dist: feedparser ==6.0.10
Requires-Dist: PyYAML ==6.0.1
Requires-Dist: Requests ==2.32.3
